{
  "warnings": [
    {
      "file": "/Users/bogdan/GitHub/CocoaLumberjack/Sources/CocoaLumberjack/Supporting Files/CocoaLumberjack.h",
      "line": 63,
      "symbol": "CocoaLumberjackVersionNumber",
      "symbol_kind": "sourcekitten.source.lang.objc.decl.constant",
      "warning": "undocumented"
    },
    {
      "file": "/Users/bogdan/GitHub/CocoaLumberjack/Sources/CocoaLumberjack/Supporting Files/CocoaLumberjack.h",
      "line": 66,
      "symbol": "CocoaLumberjackVersionString",
      "symbol_kind": "sourcekitten.source.lang.objc.decl.constant",
      "warning": "undocumented"
    }
  ],
  "source_directory": "/Users/bogdan/GitHub/CocoaLumberjack"
}